{
  "step_number": 5,
  "step_name": "Narrative Builder",
  "entity_id": "mlc",
  "entity_name": "Major League Cricket",
  "entity_type": "SPORT_LEAGUE",
  "started_at": "2026-02-19T09:04:25.110004+00:00",
  "completed_at": "2026-02-19T09:04:25.158692+00:00",
  "duration_ms": 48,
  "cost_usd": 0.0,
  "status": "success",
  "input_data": {
    "entity_id": "mlc",
    "entity_name": "Major League Cricket",
    "entity_type": "SPORT_LEAGUE",
    "max_tokens": 2000
  },
  "output_data": {
    "narrative": "# Temporal Narrative (2 episodes: 2026-02-19T08:58:17.209157+00:00 to 2026-02-19T09:04:24.465965+00:00)\n\n## Other\n\n- **2026-02-19** (Unknown): Discovery run found 2 signal(s). Final confidence: 0.52. Signals: TECHNOLOGY_ADOPTED, TECHNOLOGY_...\n- **2026-02-19** (Unknown): Discovery run found 2 signal(s). Final confidence: 0.52. Signals: TECHNOLOGY_ADOPTED, TECHNOLOGY_...\n",
    "episode_count": 2,
    "total_episodes": 2,
    "estimated_tokens": 93,
    "truncated": false
  },
  "details": "Step 5: Narrative Builder\n\nEntity: Major League Cricket\nEpisodes Available: 2\nEpisodes Included: 2\nEstimated Tokens: 93\nTruncated: False\n\nNarrative Preview (first 500 chars):\n# Temporal Narrative (2 episodes: 2026-02-19T08:58:17.209157+00:00 to 2026-02-19T09:04:24.465965+00:00)\n\n## Other\n\n- **2026-02-19** (Unknown): Discovery run found 2 signal(s). Final confidence: 0.52. Signals: TECHNOLOGY_ADOPTED, TECHNOLOGY_...\n- **2026-02-19** (Unknown): Discovery run found 2 signal(s). Final confidence: 0.52. Signals: TECHNOLOGY_ADOPTED, TECHNOLOGY_...\n...\n",
  "logs": [
    "Fetching episodes for narrative building...",
    "Retrieved 2 episodes",
    "Narrative built: 93 tokens",
    "Narrative builder completed successfully"
  ],
  "metrics": {
    "episodes_available": 2,
    "episodes_included": 2,
    "estimated_tokens": 93,
    "truncated": false
  }
}